sysdef/__init__.py
sysdef/disk_image.py
sysdef/emulator.py
sysdef/util.py
sysdef/interpreter/__init__.py
sysdef/interpreter/docker.py
sysdef/interpreter/files.py
sysdef/interpreter/groups.py
sysdef/interpreter/meta.py
sysdef/interpreter/mounts.py
sysdef/interpreter/network.py
sysdef/interpreter/overlay.py
sysdef/interpreter/pip3.py
sysdef/interpreter/swap.py
sysdef/interpreter/users.py
sysdef/res/sysdef.service
sysdef-0.0.7.dist-info/LICENSE
sysdef-0.0.7.dist-info/METADATA
sysdef-0.0.7.dist-info/WHEEL
sysdef-0.0.7.dist-info/entry_points.txt
sysdef-0.0.7.dist-info/top_level.txt
sysdef-0.0.7.dist-info/RECORD
