Metadata-Version: 2.1
Name: sysdef
Version: 0.0.7
Summary: sysdef bootable image and configuration management system
Home-page: https://github.com/geoffwilliams/sysdef
Author: Geoff Williams
Author-email: geoff@declarativesystems.com
License: UNKNOWN
Platform: UNKNOWN
Classifier: Development Status :: 1 - Planning
Classifier: Programming Language :: Python :: 3
Classifier: License :: OSI Approved :: Apache Software License
Classifier: Operating System :: OS Independent
Requires-Python: >=3.6
